[
  {
    "Id": "B12",
    "Value0": [ "あ", "ぁ", "あ゛" ],
    "Value1": [ "い", "ぃ", "い゛" ],
    "Value2": [ "う", "ぅ", "う゛" ],
    "Value3": [ "え", "ぇ", "え゛" ],
    "Value4": [ "お", "ぉ", "お゛" ],
    "ExeTags": {
      "Short": {
        "0": "write0",
        "1": "write1",
        "2": "write2",
        "3": "write3",
        "4": "write4"
      },
      "Long": {
        "0": "temp0",
        "1": "temp2",
        "2": "temp3",
        "3": "temp4",
        "4": "temp5"
      }
    }
  },
  {
    "Id": "B13",
    "Value0": [ "か", "ヵ", "が" ],
    "Value1": [ "き", "ぎ" ],
    "Value2": [ "く", "ぐ" ],
    "Value3": [ "け", "ヶ", "げ" ],
    "Value4": [ "こ", "ご" ],
    "ExeTags": {
      "Short": {
        "0": "write0",
        "1": "write1",
        "2": "write2",
        "3": "write3",
        "4": "write4"
      },
      "Long": {
        "0": "write0",
        "1": "write1",
        "2": "write2",
        "3": "write3",
        "4": "write4"
      }
    }
  },
  {
    "Id": "B23",
    "Value0": [ "な" ],
    "Value1": [ "に" ],
    "Value2": [ "ぬ" ],
    "Value3": [ "ね" ],
    "Value4": [ "の" ],
    "ExeTags": {
      "Short": {
        "0": "write0",
        "1": "write1",
        "2": "write2",
        "3": "write3",
        "4": "write4"
      },
      "Long": {
        "0": "write0",
        "1": "write1",
        "2": "write2",
        "3": "write3",
        "4": "write4"
      }
    }
  },
  {
    "Id": "B24",
    "Value0": [ "は", "ば", "ぱ" ],
    "Value1": [ "ひ", "び", "ぴ" ],
    "Value2": [ "ふ", "ぶ", "ぷ" ],
    "Value3": [ "へ", "べ", "ぺ" ],
    "Value4": [ "ほ", "ぼ", "ぽ" ],
    "ExeTags": {
      "Short": {
        "0": "write0",
        "1": "write1",
        "2": "write2",
        "3": "write3",
        "4": "write4"
      },
      "Long": {
        "0": "write0",
        "1": "write1",
        "2": "write2",
        "3": "write3",
        "4": "write4"
      }
    }
  },
  {
    "Id": "B43",
    "Value0": [ "わ", "ゎ" ],
    "Value1": [ "を" ],
    "Value2": [ "ん" ],
    "Value4": [ "" ],
    "ExeTags": {
      "Short": {
        "0": "write0",
        "1": "write1",
        "2": "write2",
        "3": "none",
        "4": "write4"
      },
      "Long": {
        "0": "write0",
        "1": "write1",
        "2": "write2",
        "3": "none",
        "4": "write4"
      }
    }
  }
]
